bolib/__init__.py
bolib/acquisition_functions/__init__.py
bolib/acquisition_functions/acquisition_function.py
bolib/acquisition_functions/expected_improvement.py
bolib/acquisition_functions/probability_of_improvement.py
bolib/acquisition_functions/upper_confidence_bound.py
bolib/objective_functions/__init__.py
bolib/objective_functions/branin.py
bolib/objective_functions/camelback.py
bolib/objective_functions/hartmann.py
bolib/objective_functions/objective_function.py
bolib/objective_functions/rastrigin.py
bolib/objective_functions/rosenbrock.py
bolib/objective_functions/schwefel.py
bolib/objective_functions/sphere.py
bolib/optimization_methods/__init__.py
bolib/optimization_methods/bayesian_optimization.py
bolib/optimization_methods/optimization_method.py
bolib/optimization_methods/random_grid.py
bolib/optimization_methods/sequential_optimization.py
bolib-0.21.0.dist-info/LICENSE.txt
bolib-0.21.0.dist-info/METADATA
bolib-0.21.0.dist-info/WHEEL
bolib-0.21.0.dist-info/top_level.txt
bolib-0.21.0.dist-info/RECORD
