Metadata-Version: 2.1
Name: bolib
Version: 0.21.0
Summary: Python library for Bayesian Optimization.
Home-page: https://gitlab.com/ibaidev/bolib
Author: Ibai Roman
Author-email: ibaidev@protonmail.com
License: GPLv3
Keywords: Bayesian Optimization Gaussian Process
Platform: UNKNOWN
Classifier: Development Status :: 4 - Beta
Classifier: Environment :: Console
Classifier: Intended Audience :: Developers
Classifier: Intended Audience :: Science/Research
Classifier: License :: OSI Approved :: GNU General Public License v3 (GPLv3)
Classifier: Operating System :: POSIX
Classifier: Programming Language :: Python
Classifier: Topic :: Scientific/Engineering :: Artificial Intelligence
License-File: LICENSE.txt
Requires-Dist: gplib
Requires-Dist: numpy
Requires-Dist: scipy
Requires-Dist: matplotlib
